pytorch_sublstm-0.0.2.dist-info/DESCRIPTION.rst
pytorch_sublstm-0.0.2.dist-info/METADATA
pytorch_sublstm-0.0.2.dist-info/RECORD
pytorch_sublstm-0.0.2.dist-info/WHEEL
pytorch_sublstm-0.0.2.dist-info/metadata.json
pytorch_sublstm-0.0.2.dist-info/top_level.txt
subLSTM/__init__.py
subLSTM/functional/__init__.py
subLSTM/functional/cell.py
subLSTM/nn/__init__.py
subLSTM/nn/cell.py
subLSTM/nn/rnn.py
