Metadata-Version: 2.0
Name: pytorch-sublstm
Version: 0.0.2
Summary: Differentiable Neural Computer, for Pytorch
Home-page: https://github.com/ixaxaar/pytorch-sublstm
Author: Russi Chatterjee
Author-email: root@ixaxaar.in
License: MIT
Keywords: cortical microcircuit pytorch sublstm
Platform: UNKNOWN
Classifier: Development Status :: 3 - Alpha
Classifier: Intended Audience :: Science/Research
Classifier: Topic :: Scientific/Engineering :: Artificial Intelligence
Classifier: License :: OSI Approved :: MIT License
Classifier: Programming Language :: Python :: 3
Classifier: Programming Language :: Python :: 3.3
Classifier: Programming Language :: Python :: 3.4
Classifier: Programming Language :: Python :: 3.5
Classifier: Programming Language :: Python :: 3.6
Requires-Python: >=3
Requires-Dist: numpy
Requires-Dist: torch
Provides-Extra: dev
Requires-Dist: check-manifest; extra == 'dev'
Provides-Extra: test
Requires-Dist: coverage; extra == 'test'
